{
  "musica.m3u": 417,
  "mexico2.m3u": 181,
  "bolivia.m3u": 23,
  "chile.m3u": 54,
  "costarica.m3u": 43,
  "espana.m3u": 153,
  "guatemala.m3u": 25,
  "puertorico.m3u": 32,
  "paraguay.m3u": 18,
  "ecuador.m3u": 44,
  "cine.m3u": 6,
  "mexico.m3u": 104,
  "colombia.m3u": 69,
  "uruguay.m3u": 4,
  "photocall_canales.m3u": 0,
  "panama.m3u": 13,
  "Argentina.m3u": 79,
  "peru.m3u": 65,
  "elsalvador.m3u": 24,
  "nicaragua.m3u": 4,
  "cuba.m3u": 2,
  "republicadominicana.m3u": 198,
  "mexico3.m3u": 188,
  "venezuela.m3u": 48,
  "honduras.m3u": 37
}