{
    "cine.m3u": 14,
    "musica.m3u": 440,
    "religion.m3u": 0,
    "espana.m3u": 144,
    "Argentina.m3u": 82,
    "mexico.m3u": 80,
    "colombia.m3u": 65,
    "chile.m3u": 49,
    "peru.m3u": 53,
    "venezuela.m3u": 36,
    "ecuador.m3u": 55,
    "republicadominicana.m3u": 202,
    "cuba.m3u": 9,
    "guatemala.m3u": 23,
    "honduras.m3u": 34,
    "elsalvador.m3u": 21,
    "nicaragua.m3u": 4,
    "costarica.m3u": 45,
    "panama.m3u": 7,
    "puertorico.m3u": 31,
    "paraguay.m3u": 48,
    "uruguay.m3u": 7,
    "bolivia.m3u": 19
}