{
    "cine.m3u": 12,
    "musica.m3u": 441,
    "religion.m3u": 0,
    "espana.m3u": 139,
    "Argentina.m3u": 79,
    "mexico.m3u": 86,
    "colombia.m3u": 69,
    "chile.m3u": 53,
    "peru.m3u": 55,
    "venezuela.m3u": 38,
    "ecuador.m3u": 61,
    "republicadominicana.m3u": 179,
    "cuba.m3u": 10,
    "guatemala.m3u": 24,
    "honduras.m3u": 32,
    "elsalvador.m3u": 17,
    "nicaragua.m3u": 4,
    "costarica.m3u": 40,
    "panama.m3u": 9,
    "puertorico.m3u": 32,
    "paraguay.m3u": 29,
    "uruguay.m3u": 6,
    "bolivia.m3u": 16
}