{
    "musica.m3u": {
        "before": 411,
        "after": 411,
        "removed": 0
    },
    "mexico2.m3u": {
        "before": 109,
        "after": 109,
        "removed": 0
    },
    "bolivia.m3u": {
        "before": 25,
        "after": 25,
        "removed": 0
    },
    "chile.m3u": {
        "before": 55,
        "after": 55,
        "removed": 0
    },
    "costarica.m3u": {
        "before": 41,
        "after": 41,
        "removed": 0
    },
    "espana.m3u": {
        "before": 155,
        "after": 155,
        "removed": 0
    },
    "guatemala.m3u": {
        "before": 22,
        "after": 22,
        "removed": 0
    },
    "puertorico.m3u": {
        "before": 32,
        "after": 32,
        "removed": 0
    },
    "paraguay.m3u": {
        "before": 19,
        "after": 19,
        "removed": 0
    },
    "ecuador.m3u": {
        "before": 38,
        "after": 38,
        "removed": 0
    },
    "cine.m3u": {
        "before": 6,
        "after": 6,
        "removed": 0
    },
    "religion.m3u": {
        "before": 0,
        "after": 0,
        "removed": 0
    },
    "mexico.m3u": {
        "before": 100,
        "after": 100,
        "removed": 0
    },
    "colombia.m3u": {
        "before": 61,
        "after": 61,
        "removed": 0
    },
    "uruguay.m3u": {
        "before": 4,
        "after": 4,
        "removed": 0
    },
    "photocall_canales.m3u": {
        "before": 0,
        "after": 0,
        "removed": 0
    },
    "panama.m3u": {
        "before": 11,
        "after": 11,
        "removed": 0
    },
    "Argentina.m3u": {
        "before": 76,
        "after": 76,
        "removed": 0
    },
    "peru.m3u": {
        "before": 61,
        "after": 61,
        "removed": 0
    },
    "elsalvador.m3u": {
        "before": 22,
        "after": 22,
        "removed": 0
    },
    "nicaragua.m3u": {
        "before": 3,
        "after": 3,
        "removed": 0
    },
    "cuba.m3u": {
        "before": 2,
        "after": 2,
        "removed": 0
    },
    "republicadominicana.m3u": {
        "before": 162,
        "after": 161,
        "removed": 1
    },
    "mexico3.m3u": {
        "before": 114,
        "after": 114,
        "removed": 0
    },
    "venezuela.m3u": {
        "before": 45,
        "after": 45,
        "removed": 0
    },
    "honduras.m3u": {
        "before": 37,
        "after": 37,
        "removed": 0
    }
}